fython/__init__.py
fython/__main__.py
fython/fame_to_python.py
fython/flatfil.pc
fython/flatfil.pro
fython/py.typed
ssb_fame_to_python-1.0.4.dist-info/LICENSE
ssb_fame_to_python-1.0.4.dist-info/METADATA
ssb_fame_to_python-1.0.4.dist-info/WHEEL
ssb_fame_to_python-1.0.4.dist-info/entry_points.txt
ssb_fame_to_python-1.0.4.dist-info/RECORD
