Metadata-Version: 2.1
Name: ssb-fame-to-python
Version: 1.0.4
Summary: SSB Fame To Python
Home-page: https://github.com/statisticsnorway/ssb-fame-to-python
License: MIT
Author: Magnus Kvåle Helliesen
Author-email: mkh@ssb.no
Requires-Python: >=3.6.2,<4.0.0
Classifier: Development Status :: 4 - Beta
Classifier: License :: OSI Approved :: MIT License
Classifier: Programming Language :: Python :: 3
Classifier: Programming Language :: Python :: 3.7
Classifier: Programming Language :: Python :: 3.8
Classifier: Programming Language :: Python :: 3.9
Classifier: Programming Language :: Python :: 3.10
Classifier: Programming Language :: Python :: 3.11
Classifier: Programming Language :: Python :: 3.12
Requires-Dist: click (>=8.0.1)
Requires-Dist: pandas (>=1.1.5) ; python_full_version >= "3.6.2" and python_version < "3.9"
Requires-Dist: pandas (>=2.2.0) ; python_version >= "3.9" and python_version < "4.0"
Requires-Dist: pandas-stubs (>=1.1.0.14) ; python_full_version >= "3.6.2" and python_version < "3.9"
Requires-Dist: pandas-stubs (>=2.1.4.231227) ; python_version >= "3.9" and python_version < "4.0"
Project-URL: Changelog, https://github.com/statisticsnorway/ssb-fame-to-python/releases
Project-URL: Documentation, https://statisticsnorway.github.io/ssb-fame-to-python
Project-URL: Repository, https://github.com/statisticsnorway/ssb-fame-to-python
